README.md
setup.py
inspiretools/__init__.py
inspiretools/functions.py
inspiretools/test_functions.py
inspiretools.egg-info/PKG-INFO
inspiretools.egg-info/SOURCES.txt
inspiretools.egg-info/dependency_links.txt
inspiretools.egg-info/entry_points.txt
inspiretools.egg-info/requires.txt
inspiretools.egg-info/top_level.txt