Metadata-Version: 2.1
Name: inspiretools
Version: 0.3
Summary: Python package to auto-generate bibliographies pulling the bibtex data from Inspire
Home-page: https://github.com/DavidMStraub/inspire-tools
Author: David M. Straub
License: UNKNOWN
Platform: UNKNOWN
